xsd_to_vol/__init__.py
xsd_to_vol/__main__.py
xsd_to_vol/schema_container.py
xsd_to_vol-0.0.6.dist-info/LICENSE.md
xsd_to_vol-0.0.6.dist-info/METADATA
xsd_to_vol-0.0.6.dist-info/WHEEL
xsd_to_vol-0.0.6.dist-info/entry_points.txt
xsd_to_vol-0.0.6.dist-info/top_level.txt
xsd_to_vol-0.0.6.dist-info/RECORD
