Metadata-Version: 2.1
Name: xsd-to-vol
Version: 0.0.6
Summary: Convert XML Schema Definitions to Voluptuous schemas.
Home-page: https://github.com/vigonotion/xsd-to-vol
Author: Tom Schneider
Author-email: mail@vigonotion.com
License: MIT
Platform: UNKNOWN
Classifier: License :: OSI Approved :: Apache Software License
Classifier: Programming Language :: Python
Classifier: Programming Language :: Python :: 3
Classifier: Programming Language :: Python :: 3.6
Classifier: Programming Language :: Python :: Implementation :: CPython
Classifier: Programming Language :: Python :: Implementation :: PyPy
Requires-Python: >=3.6.0
Requires-Dist: xmltodict
Requires-Dist: argparse
